{
  "manifestVersion": "3.2",
  "proxies": [
    {
      "address": "0x6012e2b6582413D946D631EBfA80DE23E312Ed44",
      "txHash": "0xef9217527c0844cadc80e8fdb129e1068475420867cffb25d63daff481ec84d4",
      "kind": "transparent"
    }
  ],
  "impls": {
    "472c056c09b2c2bba804837b8870cf765e7f0273c13567127dba807fe19ed08f": {
      "address": "0x3b04F7Ba038BAd27e568942f7e541DB8b6435ABA",
      "txHash": "0x210af6960bf5a5a815fb621a792addf171af675c7443808e2ff51867b069eed5",
      "layout": {
        "solcVersion": "0.8.20",
        "storage": [
          {
            "label": "message",
            "offset": 0,
            "slot": "0",
            "type": "t_string_storage",
            "contract": "Swisstronik",
            "src": "contracts/Hello_swtr.sol:5"
          }
        ],
        "types": {
          "t_string_storage": {
            "label": "string",
            "numberOfBytes": "32"
          }
        },
        "namespaces": {}
      }
    }
  }
}
